setup.py
dynconf/__init__.py
dynconf/cli.py
dynconf.egg-info/PKG-INFO
dynconf.egg-info/SOURCES.txt
dynconf.egg-info/dependency_links.txt
dynconf.egg-info/entry_points.txt
dynconf.egg-info/top_level.txt