Metadata-Version: 1.0
Name: dynconf
Version: 0.3
Summary: Configuration file proxy.
Home-page: UNKNOWN
Author: Jorge E. Cardona
Author-email: jorgeecardona@gmail.com
License: UNKNOWN
Platform: UNKNOWN
